[
  {
    "anonymous": false,
    "inputs": [{ "indexed": true, "internalType": "address", "name": "token", "type": "address" }],
    "name": "AddedRewardToken",
    "type": "event"
  },
  {
    "anonymous": false,
    "inputs": [
      { "indexed": true, "internalType": "address", "name": "owner", "type": "address" },
      { "indexed": true, "internalType": "address", "name": "spender", "type": "address" },
      { "indexed": false, "internalType": "uint256", "name": "value", "type": "uint256" }
    ],
    "name": "Approval",
    "type": "event"
  },
  {
    "anonymous": false,
    "inputs": [
      { "indexed": false, "internalType": "address", "name": "controller", "type": "address" },
      { "indexed": false, "internalType": "uint256", "name": "ts", "type": "uint256" },
      { "indexed": false, "internalType": "uint256", "name": "block", "type": "uint256" }
    ],
    "name": "ContractInitialized",
    "type": "event"
  },
  {
    "anonymous": false,
    "inputs": [
      { "indexed": true, "internalType": "address", "name": "beneficiary", "type": "address" },
      { "indexed": false, "internalType": "uint256", "name": "amount", "type": "uint256" }
    ],
    "name": "Deposit",
    "type": "event"
  },
  {
    "anonymous": false,
    "inputs": [{ "indexed": false, "internalType": "uint256", "name": "amount", "type": "uint256" }],
    "name": "Invest",
    "type": "event"
  },
  {
    "anonymous": false,
    "inputs": [{ "indexed": true, "internalType": "address", "name": "token", "type": "address" }],
    "name": "RemovedRewardToken",
    "type": "event"
  },
  {
    "anonymous": false,
    "inputs": [
      { "indexed": false, "internalType": "address", "name": "rewardToken", "type": "address" },
      { "indexed": false, "internalType": "uint256", "name": "reward", "type": "uint256" }
    ],
    "name": "RewardAdded",
    "type": "event"
  },
  {
    "anonymous": false,
    "inputs": [
      { "indexed": true, "internalType": "address", "name": "user", "type": "address" },
      { "indexed": false, "internalType": "address", "name": "rewardToken", "type": "address" },
      { "indexed": false, "internalType": "uint256", "name": "reward", "type": "uint256" }
    ],
    "name": "RewardDenied",
    "type": "event"
  },
  {
    "anonymous": false,
    "inputs": [
      { "indexed": false, "internalType": "address", "name": "rewardToken", "type": "address" },
      { "indexed": false, "internalType": "uint256", "name": "amount", "type": "uint256" }
    ],
    "name": "RewardMovedToController",
    "type": "event"
  },
  {
    "anonymous": false,
    "inputs": [
      { "indexed": true, "internalType": "address", "name": "user", "type": "address" },
      { "indexed": false, "internalType": "address", "name": "rewardToken", "type": "address" },
      { "indexed": false, "internalType": "uint256", "name": "reward", "type": "uint256" }
    ],
    "name": "RewardPaid",
    "type": "event"
  },
  {
    "anonymous": false,
    "inputs": [
      { "indexed": true, "internalType": "address", "name": "token", "type": "address" },
      { "indexed": false, "internalType": "uint256", "name": "amount", "type": "uint256" }
    ],
    "name": "RewardRecirculated",
    "type": "event"
  },
  {
    "anonymous": false,
    "inputs": [
      { "indexed": true, "internalType": "address", "name": "token", "type": "address" },
      { "indexed": false, "internalType": "uint256", "name": "amount", "type": "uint256" }
    ],
    "name": "RewardSentToController",
    "type": "event"
  },
  {
    "anonymous": false,
    "inputs": [
      { "indexed": true, "internalType": "address", "name": "user", "type": "address" },
      { "indexed": false, "internalType": "uint256", "name": "amount", "type": "uint256" }
    ],
    "name": "Staked",
    "type": "event"
  },
  {
    "anonymous": false,
    "inputs": [
      { "indexed": false, "internalType": "address", "name": "newStrategy", "type": "address" },
      { "indexed": false, "internalType": "uint256", "name": "time", "type": "uint256" }
    ],
    "name": "StrategyAnnounced",
    "type": "event"
  },
  {
    "anonymous": false,
    "inputs": [
      { "indexed": false, "internalType": "address", "name": "newStrategy", "type": "address" },
      { "indexed": false, "internalType": "address", "name": "oldStrategy", "type": "address" }
    ],
    "name": "StrategyChanged",
    "type": "event"
  },
  {
    "anonymous": false,
    "inputs": [
      { "indexed": true, "internalType": "address", "name": "from", "type": "address" },
      { "indexed": true, "internalType": "address", "name": "to", "type": "address" },
      { "indexed": false, "internalType": "uint256", "name": "value", "type": "uint256" }
    ],
    "name": "Transfer",
    "type": "event"
  },
  {
    "anonymous": false,
    "inputs": [
      { "indexed": true, "internalType": "string", "name": "name", "type": "string" },
      { "indexed": false, "internalType": "address", "name": "oldValue", "type": "address" },
      { "indexed": false, "internalType": "address", "name": "newValue", "type": "address" }
    ],
    "name": "UpdatedAddressSlot",
    "type": "event"
  },
  {
    "anonymous": false,
    "inputs": [
      { "indexed": true, "internalType": "string", "name": "name", "type": "string" },
      { "indexed": false, "internalType": "bool", "name": "oldValue", "type": "bool" },
      { "indexed": false, "internalType": "bool", "name": "newValue", "type": "bool" }
    ],
    "name": "UpdatedBoolSlot",
    "type": "event"
  },
  {
    "anonymous": false,
    "inputs": [
      { "indexed": true, "internalType": "string", "name": "name", "type": "string" },
      { "indexed": false, "internalType": "uint256", "name": "oldValue", "type": "uint256" },
      { "indexed": false, "internalType": "uint256", "name": "newValue", "type": "uint256" }
    ],
    "name": "UpdatedUint256Slot",
    "type": "event"
  },
  {
    "anonymous": false,
    "inputs": [
      { "indexed": true, "internalType": "address", "name": "beneficiary", "type": "address" },
      { "indexed": false, "internalType": "uint256", "name": "amount", "type": "uint256" }
    ],
    "name": "Withdraw",
    "type": "event"
  },
  {
    "anonymous": false,
    "inputs": [
      { "indexed": true, "internalType": "address", "name": "user", "type": "address" },
      { "indexed": false, "internalType": "uint256", "name": "amount", "type": "uint256" }
    ],
    "name": "Withdrawn",
    "type": "event"
  },
  {
    "inputs": [],
    "name": "DEPOSIT_FEE_DENOMINATOR",
    "outputs": [{ "internalType": "uint256", "name": "", "type": "uint256" }],
    "stateMutability": "view",
    "type": "function"
  },
  {
    "inputs": [],
    "name": "LOCK_PENALTY_DENOMINATOR",
    "outputs": [{ "internalType": "uint256", "name": "", "type": "uint256" }],
    "stateMutability": "view",
    "type": "function"
  },
  {
    "inputs": [],
    "name": "TO_INVEST_DENOMINATOR",
    "outputs": [{ "internalType": "uint256", "name": "", "type": "uint256" }],
    "stateMutability": "view",
    "type": "function"
  },
  {
    "inputs": [],
    "name": "VERSION",
    "outputs": [{ "internalType": "string", "name": "", "type": "string" }],
    "stateMutability": "view",
    "type": "function"
  },
  {
    "inputs": [],
    "name": "active",
    "outputs": [{ "internalType": "bool", "name": "", "type": "bool" }],
    "stateMutability": "view",
    "type": "function"
  },
  {
    "inputs": [{ "internalType": "address", "name": "rt", "type": "address" }],
    "name": "addRewardToken",
    "outputs": [],
    "stateMutability": "nonpayable",
    "type": "function"
  },
  {
    "inputs": [
      { "internalType": "address", "name": "owner", "type": "address" },
      { "internalType": "address", "name": "spender", "type": "address" }
    ],
    "name": "allowance",
    "outputs": [{ "internalType": "uint256", "name": "", "type": "uint256" }],
    "stateMutability": "view",
    "type": "function"
  },
  {
    "inputs": [],
    "name": "alwaysInvest",
    "outputs": [{ "internalType": "bool", "name": "", "type": "bool" }],
    "stateMutability": "view",
    "type": "function"
  },
  {
    "inputs": [
      { "internalType": "address", "name": "spender", "type": "address" },
      { "internalType": "uint256", "name": "amount", "type": "uint256" }
    ],
    "name": "approve",
    "outputs": [{ "internalType": "bool", "name": "", "type": "bool" }],
    "stateMutability": "nonpayable",
    "type": "function"
  },
  {
    "inputs": [],
    "name": "availableToInvestOut",
    "outputs": [{ "internalType": "uint256", "name": "", "type": "uint256" }],
    "stateMutability": "view",
    "type": "function"
  },
  {
    "inputs": [{ "internalType": "address", "name": "account", "type": "address" }],
    "name": "balanceOf",
    "outputs": [{ "internalType": "uint256", "name": "", "type": "uint256" }],
    "stateMutability": "view",
    "type": "function"
  },
  {
    "inputs": [{ "internalType": "bool", "name": "_active", "type": "bool" }],
    "name": "changeActivityStatus",
    "outputs": [],
    "stateMutability": "nonpayable",
    "type": "function"
  },
  {
    "inputs": [{ "internalType": "bool", "name": "_active", "type": "bool" }],
    "name": "changeAlwaysInvest",
    "outputs": [],
    "stateMutability": "nonpayable",
    "type": "function"
  },
  {
    "inputs": [{ "internalType": "bool", "name": "_active", "type": "bool" }],
    "name": "changeDoHardWorkOnInvest",
    "outputs": [],
    "stateMutability": "nonpayable",
    "type": "function"
  },
  {
    "inputs": [{ "internalType": "bool", "name": "_value", "type": "bool" }],
    "name": "changePpfsDecreaseAllowed",
    "outputs": [],
    "stateMutability": "nonpayable",
    "type": "function"
  },
  {
    "inputs": [{ "internalType": "bool", "name": "_active", "type": "bool" }],
    "name": "changeProtectionMode",
    "outputs": [],
    "stateMutability": "nonpayable",
    "type": "function"
  },
  {
    "inputs": [],
    "name": "controller",
    "outputs": [{ "internalType": "address", "name": "", "type": "address" }],
    "stateMutability": "view",
    "type": "function"
  },
  {
    "inputs": [],
    "name": "created",
    "outputs": [{ "internalType": "uint256", "name": "ts", "type": "uint256" }],
    "stateMutability": "view",
    "type": "function"
  },
  {
    "inputs": [],
    "name": "createdBlock",
    "outputs": [{ "internalType": "uint256", "name": "ts", "type": "uint256" }],
    "stateMutability": "view",
    "type": "function"
  },
  {
    "inputs": [],
    "name": "decimals",
    "outputs": [{ "internalType": "uint8", "name": "", "type": "uint8" }],
    "stateMutability": "view",
    "type": "function"
  },
  {
    "inputs": [
      { "internalType": "address", "name": "spender", "type": "address" },
      { "internalType": "uint256", "name": "subtractedValue", "type": "uint256" }
    ],
    "name": "decreaseAllowance",
    "outputs": [{ "internalType": "bool", "name": "", "type": "bool" }],
    "stateMutability": "nonpayable",
    "type": "function"
  },
  {
    "inputs": [{ "internalType": "uint256", "name": "amount", "type": "uint256" }],
    "name": "deposit",
    "outputs": [],
    "stateMutability": "nonpayable",
    "type": "function"
  },
  {
    "inputs": [{ "internalType": "uint256", "name": "amount", "type": "uint256" }],
    "name": "depositAndInvest",
    "outputs": [],
    "stateMutability": "nonpayable",
    "type": "function"
  },
  {
    "inputs": [],
    "name": "depositFeeNumerator",
    "outputs": [{ "internalType": "uint256", "name": "", "type": "uint256" }],
    "stateMutability": "view",
    "type": "function"
  },
  {
    "inputs": [
      { "internalType": "uint256", "name": "amount", "type": "uint256" },
      { "internalType": "address", "name": "holder", "type": "address" }
    ],
    "name": "depositFor",
    "outputs": [],
    "stateMutability": "nonpayable",
    "type": "function"
  },
  { "inputs": [], "name": "disableLock", "outputs": [], "stateMutability": "nonpayable", "type": "function" },
  { "inputs": [], "name": "doHardWork", "outputs": [], "stateMutability": "nonpayable", "type": "function" },
  {
    "inputs": [],
    "name": "doHardWorkOnInvest",
    "outputs": [{ "internalType": "bool", "name": "", "type": "bool" }],
    "stateMutability": "view",
    "type": "function"
  },
  {
    "inputs": [],
    "name": "duration",
    "outputs": [{ "internalType": "uint256", "name": "", "type": "uint256" }],
    "stateMutability": "view",
    "type": "function"
  },
  {
    "inputs": [
      { "internalType": "address", "name": "rt", "type": "address" },
      { "internalType": "address", "name": "account", "type": "address" }
    ],
    "name": "earned",
    "outputs": [{ "internalType": "uint256", "name": "", "type": "uint256" }],
    "stateMutability": "view",
    "type": "function"
  },
  {
    "inputs": [
      { "internalType": "address", "name": "rt", "type": "address" },
      { "internalType": "address", "name": "account", "type": "address" }
    ],
    "name": "earnedWithBoost",
    "outputs": [{ "internalType": "uint256", "name": "", "type": "uint256" }],
    "stateMutability": "view",
    "type": "function"
  },
  { "inputs": [], "name": "exit", "outputs": [], "stateMutability": "nonpayable", "type": "function" },
  { "inputs": [], "name": "getAllRewards", "outputs": [], "stateMutability": "nonpayable", "type": "function" },
  {
    "inputs": [{ "internalType": "address", "name": "rewardsReceiver", "type": "address" }],
    "name": "getAllRewardsFor",
    "outputs": [],
    "stateMutability": "nonpayable",
    "type": "function"
  },
  {
    "inputs": [],
    "name": "getPricePerFullShare",
    "outputs": [{ "internalType": "uint256", "name": "", "type": "uint256" }],
    "stateMutability": "view",
    "type": "function"
  },
  {
    "inputs": [{ "internalType": "address", "name": "rt", "type": "address" }],
    "name": "getReward",
    "outputs": [],
    "stateMutability": "nonpayable",
    "type": "function"
  },
  {
    "inputs": [{ "internalType": "address", "name": "rt", "type": "address" }],
    "name": "getRewardTokenIndex",
    "outputs": [{ "internalType": "uint256", "name": "", "type": "uint256" }],
    "stateMutability": "view",
    "type": "function"
  },
  {
    "inputs": [
      { "internalType": "address", "name": "spender", "type": "address" },
      { "internalType": "uint256", "name": "addedValue", "type": "uint256" }
    ],
    "name": "increaseAllowance",
    "outputs": [{ "internalType": "bool", "name": "", "type": "bool" }],
    "stateMutability": "nonpayable",
    "type": "function"
  },
  {
    "inputs": [{ "internalType": "address", "name": "__controller", "type": "address" }],
    "name": "initializeControllable",
    "outputs": [],
    "stateMutability": "nonpayable",
    "type": "function"
  },
  {
    "inputs": [
      { "internalType": "string", "name": "_name", "type": "string" },
      { "internalType": "string", "name": "_symbol", "type": "string" },
      { "internalType": "address", "name": "_controller", "type": "address" },
      { "internalType": "address", "name": "__underlying", "type": "address" },
      { "internalType": "uint256", "name": "_duration", "type": "uint256" },
      { "internalType": "bool", "name": "_lockAllowed", "type": "bool" },
      { "internalType": "address", "name": "_rewardToken", "type": "address" },
      { "internalType": "uint256", "name": "_depositFee", "type": "uint256" }
    ],
    "name": "initializeSmartVault",
    "outputs": [],
    "stateMutability": "nonpayable",
    "type": "function"
  },
  {
    "inputs": [
      { "internalType": "address", "name": "_underlyingToken", "type": "address" },
      { "internalType": "uint256", "name": "_durationValue", "type": "uint256" },
      { "internalType": "bool", "name": "__lockAllowed", "type": "bool" }
    ],
    "name": "initializeVaultStorage",
    "outputs": [],
    "stateMutability": "nonpayable",
    "type": "function"
  },
  {
    "inputs": [{ "internalType": "address", "name": "_value", "type": "address" }],
    "name": "isController",
    "outputs": [{ "internalType": "bool", "name": "", "type": "bool" }],
    "stateMutability": "view",
    "type": "function"
  },
  {
    "inputs": [{ "internalType": "address", "name": "_value", "type": "address" }],
    "name": "isGovernance",
    "outputs": [{ "internalType": "bool", "name": "", "type": "bool" }],
    "stateMutability": "view",
    "type": "function"
  },
  {
    "inputs": [{ "internalType": "address", "name": "rt", "type": "address" }],
    "name": "lastTimeRewardApplicable",
    "outputs": [{ "internalType": "uint256", "name": "", "type": "uint256" }],
    "stateMutability": "view",
    "type": "function"
  },
  {
    "inputs": [{ "internalType": "address", "name": "", "type": "address" }],
    "name": "lastUpdateTimeForToken",
    "outputs": [{ "internalType": "uint256", "name": "", "type": "uint256" }],
    "stateMutability": "view",
    "type": "function"
  },
  {
    "inputs": [],
    "name": "lockAllowed",
    "outputs": [{ "internalType": "bool", "name": "", "type": "bool" }],
    "stateMutability": "view",
    "type": "function"
  },
  {
    "inputs": [],
    "name": "lockPenalty",
    "outputs": [{ "internalType": "uint256", "name": "", "type": "uint256" }],
    "stateMutability": "view",
    "type": "function"
  },
  {
    "inputs": [],
    "name": "lockPeriod",
    "outputs": [{ "internalType": "uint256", "name": "", "type": "uint256" }],
    "stateMutability": "view",
    "type": "function"
  },
  {
    "inputs": [],
    "name": "name",
    "outputs": [{ "internalType": "string", "name": "", "type": "string" }],
    "stateMutability": "view",
    "type": "function"
  },
  {
    "inputs": [
      { "internalType": "address", "name": "_rewardToken", "type": "address" },
      { "internalType": "uint256", "name": "_amount", "type": "uint256" }
    ],
    "name": "notifyRewardWithoutPeriodChange",
    "outputs": [],
    "stateMutability": "nonpayable",
    "type": "function"
  },
  {
    "inputs": [
      { "internalType": "address", "name": "_rewardToken", "type": "address" },
      { "internalType": "uint256", "name": "amount", "type": "uint256" }
    ],
    "name": "notifyTargetRewardAmount",
    "outputs": [],
    "stateMutability": "nonpayable",
    "type": "function"
  },
  {
    "inputs": [{ "internalType": "string", "name": "value", "type": "string" }],
    "name": "overrideName",
    "outputs": [],
    "stateMutability": "nonpayable",
    "type": "function"
  },
  {
    "inputs": [{ "internalType": "string", "name": "value", "type": "string" }],
    "name": "overrideSymbol",
    "outputs": [],
    "stateMutability": "nonpayable",
    "type": "function"
  },
  {
    "inputs": [{ "internalType": "address", "name": "", "type": "address" }],
    "name": "periodFinishForToken",
    "outputs": [{ "internalType": "uint256", "name": "", "type": "uint256" }],
    "stateMutability": "view",
    "type": "function"
  },
  {
    "inputs": [],
    "name": "ppfsDecreaseAllowed",
    "outputs": [{ "internalType": "bool", "name": "", "type": "bool" }],
    "stateMutability": "view",
    "type": "function"
  },
  {
    "inputs": [],
    "name": "protectionMode",
    "outputs": [{ "internalType": "bool", "name": "", "type": "bool" }],
    "stateMutability": "view",
    "type": "function"
  },
  { "inputs": [], "name": "rebalance", "outputs": [], "stateMutability": "nonpayable", "type": "function" },
  {
    "inputs": [{ "internalType": "address", "name": "rt", "type": "address" }],
    "name": "removeRewardToken",
    "outputs": [],
    "stateMutability": "nonpayable",
    "type": "function"
  },
  {
    "inputs": [{ "internalType": "address", "name": "rt", "type": "address" }],
    "name": "rewardPerToken",
    "outputs": [{ "internalType": "uint256", "name": "", "type": "uint256" }],
    "stateMutability": "view",
    "type": "function"
  },
  {
    "inputs": [{ "internalType": "address", "name": "", "type": "address" }],
    "name": "rewardPerTokenStoredForToken",
    "outputs": [{ "internalType": "uint256", "name": "", "type": "uint256" }],
    "stateMutability": "view",
    "type": "function"
  },
  {
    "inputs": [{ "internalType": "address", "name": "", "type": "address" }],
    "name": "rewardRateForToken",
    "outputs": [{ "internalType": "uint256", "name": "", "type": "uint256" }],
    "stateMutability": "view",
    "type": "function"
  },
  {
    "inputs": [],
    "name": "rewardTokens",
    "outputs": [{ "internalType": "address[]", "name": "", "type": "address[]" }],
    "stateMutability": "view",
    "type": "function"
  },
  {
    "inputs": [],
    "name": "rewardTokensLength",
    "outputs": [{ "internalType": "uint256", "name": "", "type": "uint256" }],
    "stateMutability": "view",
    "type": "function"
  },
  {
    "inputs": [
      { "internalType": "address", "name": "", "type": "address" },
      { "internalType": "address", "name": "", "type": "address" }
    ],
    "name": "rewardsForToken",
    "outputs": [{ "internalType": "uint256", "name": "", "type": "uint256" }],
    "stateMutability": "view",
    "type": "function"
  },
  {
    "inputs": [{ "internalType": "uint256", "name": "_value", "type": "uint256" }],
    "name": "setLockPenalty",
    "outputs": [],
    "stateMutability": "nonpayable",
    "type": "function"
  },
  {
    "inputs": [{ "internalType": "uint256", "name": "_value", "type": "uint256" }],
    "name": "setLockPeriod",
    "outputs": [],
    "stateMutability": "nonpayable",
    "type": "function"
  },
  {
    "inputs": [{ "internalType": "address", "name": "newStrategy", "type": "address" }],
    "name": "setStrategy",
    "outputs": [],
    "stateMutability": "nonpayable",
    "type": "function"
  },
  {
    "inputs": [{ "internalType": "uint256", "name": "_value", "type": "uint256" }],
    "name": "setToInvest",
    "outputs": [],
    "stateMutability": "nonpayable",
    "type": "function"
  },
  { "inputs": [], "name": "stop", "outputs": [], "stateMutability": "nonpayable", "type": "function" },
  {
    "inputs": [],
    "name": "strategy",
    "outputs": [{ "internalType": "address", "name": "", "type": "address" }],
    "stateMutability": "view",
    "type": "function"
  },
  {
    "inputs": [],
    "name": "symbol",
    "outputs": [{ "internalType": "string", "name": "", "type": "string" }],
    "stateMutability": "view",
    "type": "function"
  },
  {
    "inputs": [],
    "name": "toInvest",
    "outputs": [{ "internalType": "uint256", "name": "", "type": "uint256" }],
    "stateMutability": "view",
    "type": "function"
  },
  {
    "inputs": [],
    "name": "totalSupply",
    "outputs": [{ "internalType": "uint256", "name": "", "type": "uint256" }],
    "stateMutability": "view",
    "type": "function"
  },
  {
    "inputs": [
      { "internalType": "address", "name": "recipient", "type": "address" },
      { "internalType": "uint256", "name": "amount", "type": "uint256" }
    ],
    "name": "transfer",
    "outputs": [{ "internalType": "bool", "name": "", "type": "bool" }],
    "stateMutability": "nonpayable",
    "type": "function"
  },
  {
    "inputs": [
      { "internalType": "address", "name": "sender", "type": "address" },
      { "internalType": "address", "name": "recipient", "type": "address" },
      { "internalType": "uint256", "name": "amount", "type": "uint256" }
    ],
    "name": "transferFrom",
    "outputs": [{ "internalType": "bool", "name": "", "type": "bool" }],
    "stateMutability": "nonpayable",
    "type": "function"
  },
  {
    "inputs": [],
    "name": "underlying",
    "outputs": [{ "internalType": "address", "name": "", "type": "address" }],
    "stateMutability": "view",
    "type": "function"
  },
  {
    "inputs": [],
    "name": "underlyingBalanceInVault",
    "outputs": [{ "internalType": "uint256", "name": "", "type": "uint256" }],
    "stateMutability": "view",
    "type": "function"
  },
  {
    "inputs": [],
    "name": "underlyingBalanceWithInvestment",
    "outputs": [{ "internalType": "uint256", "name": "", "type": "uint256" }],
    "stateMutability": "view",
    "type": "function"
  },
  {
    "inputs": [{ "internalType": "address", "name": "holder", "type": "address" }],
    "name": "underlyingBalanceWithInvestmentForHolder",
    "outputs": [{ "internalType": "uint256", "name": "", "type": "uint256" }],
    "stateMutability": "view",
    "type": "function"
  },
  {
    "inputs": [],
    "name": "underlyingUnit",
    "outputs": [{ "internalType": "uint256", "name": "", "type": "uint256" }],
    "stateMutability": "view",
    "type": "function"
  },
  {
    "inputs": [{ "internalType": "address", "name": "", "type": "address" }],
    "name": "userBoostTs",
    "outputs": [{ "internalType": "uint256", "name": "", "type": "uint256" }],
    "stateMutability": "view",
    "type": "function"
  },
  {
    "inputs": [{ "internalType": "address", "name": "", "type": "address" }],
    "name": "userLastDepositTs",
    "outputs": [{ "internalType": "uint256", "name": "", "type": "uint256" }],
    "stateMutability": "view",
    "type": "function"
  },
  {
    "inputs": [{ "internalType": "address", "name": "", "type": "address" }],
    "name": "userLastWithdrawTs",
    "outputs": [{ "internalType": "uint256", "name": "", "type": "uint256" }],
    "stateMutability": "view",
    "type": "function"
  },
  {
    "inputs": [{ "internalType": "address", "name": "", "type": "address" }],
    "name": "userLockTs",
    "outputs": [{ "internalType": "uint256", "name": "", "type": "uint256" }],
    "stateMutability": "view",
    "type": "function"
  },
  {
    "inputs": [
      { "internalType": "address", "name": "", "type": "address" },
      { "internalType": "address", "name": "", "type": "address" }
    ],
    "name": "userRewardPerTokenPaidForToken",
    "outputs": [{ "internalType": "uint256", "name": "", "type": "uint256" }],
    "stateMutability": "view",
    "type": "function"
  },
  {
    "inputs": [{ "internalType": "uint256", "name": "numberOfShares", "type": "uint256" }],
    "name": "withdraw",
    "outputs": [],
    "stateMutability": "nonpayable",
    "type": "function"
  },
  { "inputs": [], "name": "withdrawAllToVault", "outputs": [], "stateMutability": "nonpayable", "type": "function" }
]
